quantagonia/__about__.py
quantagonia/__init__.py
quantagonia/cli.py
quantagonia/enums.py
quantagonia/extras.py
quantagonia/parameters.py
quantagonia/cloud/__init__.py
quantagonia/cloud/cloud_runner.py
quantagonia/cloud/enums.py
quantagonia/cloud/https_client.py
quantagonia/cloud/solver_log.py
quantagonia/cloud/dto/__init__.py
quantagonia/cloud/dto/encoder.py
quantagonia/cloud/dto/job.py
quantagonia/cloud/dto/presigned_s3.py
quantagonia/errors/__init__.py
quantagonia/errors/errors.py
quantagonia/mip/__init__.py
quantagonia/mip/model.py
quantagonia/mip/pulp_adapter.py
quantagonia/mip/variable.py
quantagonia/mip/wrappers/__init__.py
quantagonia/mip/wrappers/cplex.py
quantagonia/mip/wrappers/gurobipy.py
quantagonia/mip/wrappers/python_mip.py
quantagonia/mip/wrappers/tupledict.py
quantagonia/mip/wrappers/wrapper_enums.py
quantagonia/parser/__init__.py
quantagonia/parser/log_parser.py
quantagonia/parser/solution_parser.py
quantagonia/qubo/__init__.py
quantagonia/qubo/expression.py
quantagonia/qubo/model.py
quantagonia/qubo/overloads.py
quantagonia/qubo/term.py
quantagonia/qubo/variable.py
quantagonia-0.14.0.dist-info/METADATA
quantagonia-0.14.0.dist-info/WHEEL
quantagonia-0.14.0.dist-info/entry_points.txt
quantagonia-0.14.0.dist-info/licenses/LICENSE
quantagonia-0.14.0.dist-info/RECORD
