Metadata-Version: 2.4
Name: quantagonia
Version: 0.14.0
Summary: This package contains the CLI and API to access Quantagonia's HybridSolver.
Project-URL: Homepage, https://www.quantagonia.com
Author-email: Quantagonia GmbH <support@quantagonia.com>
License: Copyright 2022 Quantagonia GmbH
License-File: LICENSE
Keywords: Linear Programming,Operations Research,Optimization
Classifier: Development Status :: 5 - Production/Stable
Classifier: Environment :: Console
Classifier: Intended Audience :: Science/Research
Classifier: License :: OSI Approved :: BSD License
Classifier: Natural Language :: English
Classifier: Programming Language :: Python
Classifier: Topic :: Scientific/Engineering :: Mathematics
Requires-Python: <3.13,>=3.8
Requires-Dist: pulp<3.0
Requires-Dist: pyscipopt>=5.5
Requires-Dist: requests
Requires-Dist: rich
Requires-Dist: semantic-version
Requires-Dist: typer
Requires-Dist: urllib3>=1.26
Requires-Dist: yaspin
Provides-Extra: qubo
Requires-Dist: dimod; extra == 'qubo'
Requires-Dist: dwave-ocean-sdk; extra == 'qubo'
Requires-Dist: numpy<2; extra == 'qubo'
Requires-Dist: pyqubo; extra == 'qubo'
Requires-Dist: qiskit; extra == 'qubo'
Requires-Dist: qiskit-optimization; extra == 'qubo'
